{
  "id": "46-trial-46",
  "name": "Trial 46",
  "width": 8,
  "height": 8,
  "start": {
    "x": 5,
    "y": 6
  },
  "exit": {
    "x": 7,
    "y": 7,
    "dir": "S"
  },
  "walls": [
    {
      "x": 6,
      "y": 0,
      "dir": "E"
    },
    {
      "x": 7,
      "y": 0,
      "dir": "S"
    },
    {
      "x": 2,
      "y": 1,
      "dir": "S"
    },
    {
      "x": 3,
      "y": 1,
      "dir": "E"
    },
    {
      "x": 2,
      "y": 3,
      "dir": "E"
    },
    {
      "x": 3,
      "y": 3,
      "dir": "E"
    },
    {
      "x": 2,
      "y": 4,
      "dir": "E"
    },
    {
      "x": 6,
      "y": 5,
      "dir": "S"
    },
    {
      "x": 2,
      "y": 6,
      "dir": "S"
    },
    {
      "x": 5,
      "y": 6,
      "dir": "S"
    }
  ],
  "traps": [
    {
      "x": 6,
      "y": 4
    },
    {
      "x": 3,
      "y": 7
    }
  ],
  "monsters": [
    {
      "kind": "mummy_white",
      "x": 6,
      "y": 4
    },
    {
      "kind": "mummy_red",
      "x": 7,
      "y": 1
    },
    {
      "kind": "scorpion_red",
      "x": 4,
      "y": 6
    },
    {
      "kind": "scorpion_white",
      "x": 7,
      "y": 3
    }
  ],
  "par": 4
}
